MANIFEST.in
README.md
requirements.txt
setup.cfg
setup.py
test-requirements.txt
simpledeploy/__init__.py
simpledeploy/build.py
simpledeploy/deploy.py
simpledeploy/destroy.py
simpledeploy/modify.py
simpledeploy.egg-info/PKG-INFO
simpledeploy.egg-info/SOURCES.txt
simpledeploy.egg-info/dependency_links.txt
simpledeploy.egg-info/entry_points.txt
simpledeploy.egg-info/requires.txt
simpledeploy.egg-info/top_level.txt
simpledeploy/dockerfile/__init__.py